openteleop/__init__.py
openteleop/main.py
openteleop-0.0.14.dist-info/METADATA
openteleop-0.0.14.dist-info/WHEEL
openteleop-0.0.14.dist-info/top_level.txt
openteleop-0.0.14.dist-info/RECORD
