Metadata-Version: 2.1
Name: openteleop
Version: 0.0.14
Summary: Python SDK for OpenTeleop
Home-page: https://github.com/openteleop/openteleop-py
Author: Devon Copeland
Author-email: founders@serial.io
License: MIT
Classifier: License :: OSI Approved :: MIT License
Classifier: Programming Language :: Python
Classifier: Programming Language :: Python :: 3
Classifier: Programming Language :: Python :: 3.11
Requires-Dist: requests
